sqlextension/__init__.py
sqlextension/expression.py
sqlextension/operators.py
sqlextension/sqlaggregat.py
sqlextension/sqlfunction.py
mds_sqlextension-0.1.11.dist-info/METADATA
mds_sqlextension-0.1.11.dist-info/WHEEL
mds_sqlextension-0.1.11.dist-info/top_level.txt
mds_sqlextension-0.1.11.dist-info/RECORD
