Metadata-Version: 2.1
Name: mds-sqlextension
Version: 0.1.11
Summary: Library to use more sql-commands
Home-page: https://www.m-ds.de/
Author: m-ds
Author-email: service@m-ds.de
License: GPL-3
Keywords: sql library
Platform: UNKNOWN
Classifier: Development Status :: 5 - Production/Stable
Classifier: Intended Audience :: Developers
Classifier: License :: OSI Approved :: BSD License
Classifier: Operating System :: OS Independent
Classifier: Programming Language :: Python :: 2.6
Classifier: Programming Language :: Python :: 2.7
Classifier: Programming Language :: Python :: 3.4
Classifier: Programming Language :: Python :: 3.5
Classifier: Programming Language :: Python :: 3.6
Classifier: Topic :: Database
Classifier: Topic :: Software Development :: Libraries :: Python Modules
Requires-Dist: python-sql (>=0.9)
